setup.py
app/__init__.py
app/cmd.py
app/main.py
app/settings.py
app/data/__init__.py
app/data/requirements.txt
app/project/__init__.py
app/project/app/__init__.py
app/project/app/controller/__init__.py
app/project/app/models/__init__.py
app/project/app/schemas/__init__.py
app/project/app/service/__init__.py
app/project/common/__init__.py
app/project/common/dependencies.py
app/project/common/middlewares.py
app/project/common/pagination.py
app/project/common/response_code.py
app/project/core/__init__.py
app/project/core/application.py
app/project/core/logger.py
app/project/core/register.py
app/project/core/security.py
app/project/core/config/__init__.py
app/project/core/config/config.py
app/project/core/config/settings.toml
fastapi_d_cli.egg-info/PKG-INFO
fastapi_d_cli.egg-info/SOURCES.txt
fastapi_d_cli.egg-info/dependency_links.txt
fastapi_d_cli.egg-info/entry_points.txt
fastapi_d_cli.egg-info/top_level.txt