Metadata-Version: 2.1
Name: fastapi-d-cli
Version: 0.0.6
Summary: FastAPI脚手架
Home-page: http://bitbucket.org/tarek/distribute/issues/
Author: Desire
Author-email: 
License: Apache Software License
Keywords: fastapi
Platform: UNKNOWN
Requires-Python: >=3.6
